Metadata-Version: 2.1
Name: testgokoro
Version: 0.0.1.dev2
Summary: testgokoro package
Home-page: UNKNOWN
Author: gokoro
Author-email: 
License: MIT
Platform: UNKNOWN
